<vector android:height="160dp" android:viewportHeight="630"
    android:viewportWidth="945" android:width="240dp" xmlns:android="http://schemas.android.com/apk/res/android">
    <path android:fillColor="#fff" android:pathData="m0,0h945v630h-945z"/>
    <path android:fillColor="#0038a8" android:pathData="m350,70l595,0l0,70l-595,0z"/>
    <path android:fillColor="#0038a8" android:pathData="m350,210l595,0l0,70l-595,0z"/>
    <path android:fillColor="#0038a8" android:pathData="m0,350l945,0l0,70l-945,0z"/>
    <path android:fillColor="#0038a8" android:pathData="m0,490l945,0l0,70l-945,0z"/>
    <path
        android:fillColor="#fcd116"
        android:pathData="m167.075,209.223 l11.586,17.301c-47.609,34.453 -18.543,54.827 -52.282,65.856 20.984,-20.479 -2.774,-23.637 14.906,-66.32"
        android:strokeColor="#7b3f00"
        android:strokeWidth="2.30929136"/>
    <path
        android:fillColor="#fcd116"
        android:pathData="m145.197,193.596 l-4.041,20.426c-58.027,-9.302 -51.881,25.657 -83.536,9.598 29.319,0.357 15.415,-18.935 58.098,-36.615"
        android:strokeColor="#7b3f00"
        android:strokeWidth="2.30999994"/>
    <path
        android:fillColor="#7b3f00"
        android:pathData="m145.199,193.599 l-9.142,-1.647 0.094,0.378c-24.39,5.977 -37.633,16.088 -48.006,23.773 -5.189,3.841 -9.666,7.108 -14.521,8.878a21.783,21.783 0,0 1,-10.074 1.214c25.178,8.944 23.511,-20.836 77.609,-12.165z"
        android:strokeColor="#7b3f00"
        android:strokeWidth="1.05104995"/>
    <path 
        android:pathData="M135.873,191.207C86.687,203.246 82.035,232.26 57.621,223.62"
        android:strokeColor="#7b3f00"
        android:strokeWidth="2.30999994"/>
    <path
        android:fillColor="#fcd116"
        android:pathData="M175,175 L158.665,158.666 85.162,264.838 191.334,191.335 175,175 85.162,264.838"
        android:strokeColor="#7b3f00"
        android:strokeWidth="2.30929136"/>
    <path
        android:fillColor="#fcd116"
        android:pathData="m140.777,167.076 l-17.301,11.586C89.023,131.053 68.649,160.119 57.621,126.38c20.479,20.984 23.833,-2.735 66.516,14.945"
        android:strokeColor="#7b3f00"
        android:strokeWidth="2.30999994"/>
    <path
        android:fillColor="#7b3f00"
        android:pathData="m140.776,167.079 l-5.299,-7.629 -0.201,0.334C113.803,146.764 97.289,144.549 84.52,142.648 78.135,141.695 72.659,140.84 67.975,138.658a21.783,21.783 0,0 1,-7.981 -6.265c11.479,24.128 31.358,1.892 63.48,46.276z"
        android:strokeColor="#7b3f00"
        android:strokeWidth="1.05104995"/>
    <path 
        android:pathData="M135.873,158.794C92.58,132.527 68.775,149.753 57.621,126.38"
        android:strokeColor="#7b3f00"
        android:strokeWidth="2.30999994"/>
    <path
        android:fillColor="#fcd116"
        android:pathData="m175,175v-23.1l-127.05,23.1 127.05,23.1v-23.1L47.95,175"
        android:strokeColor="#7b3f00"
        android:strokeWidth="2.30999994"/>
    <path
        android:fillColor="#7b3f00"
        android:pathData="m175,175v23.1,-23.1L47.95,175l127.05,23.1"/>
    <path
        android:fillColor="#fcd116"
        android:pathData="m156.404,145.198 l-20.426,-4.041c9.302,-58.027 -25.657,-51.881 -9.598,-83.536 -0.357,29.319 19.925,17.76 37.605,60.443"
        android:strokeColor="#7b3f00"
        android:strokeWidth="2.30999994"/>
    <path
        android:fillColor="#7b3f00"
        android:pathData="m156.401,145.199 l1.647,-9.142 -0.378,0.094c-5.977,-24.39 -16.088,-37.633 -23.773,-48.006 -3.841,-5.189 -7.108,-9.666 -8.878,-14.521a21.783,21.783 0,0 1,-1.214 -10.074c-8.944,25.178 20.836,23.511 12.165,77.609z"
        android:strokeColor="#7b3f00"
        android:strokeWidth="1.05104995"/>
    <path 
        android:pathData="M158.793,135.874C146.754,86.687 117.74,82.036 126.38,57.621"
        android:strokeColor="#7b3f00"
        android:strokeWidth="2.30999994"/>
    <path
        android:fillColor="#fcd116"
        android:pathData="M175,175 L191.334,158.666 85.162,85.162 158.665,191.335 175,175 85.162,85.162"
        android:strokeColor="#7b3f00"
        android:strokeWidth="2.30999994"/>
    <path
        android:fillColor="#7b3f00"
        android:pathData="M175,175 L158.665,191.335 175,175 85.162,85.162 158.665,191.335"/>
    <path
        android:fillColor="#fcd116"
        android:pathData="M182.924,140.778 L171.338,123.477c47.609,-34.454 18.543,-54.827 52.282,-65.856 -20.984,20.479 2.652,23.856 -15.028,66.539"
        android:strokeColor="#7b3f00"
        android:strokeWidth="2.30999994"/>
    <path
        android:fillColor="#7b3f00"
        android:pathData="m182.921,140.776 l7.629,-5.299 -0.334,-0.201c13.02,-21.473 15.235,-37.987 17.136,-50.756 0.953,-6.385 1.808,-11.861 3.99,-16.545a21.783,21.783 0,0 1,6.265 -7.981C193.479,71.473 215.715,91.352 171.331,123.474Z"
        android:strokeColor="#7b3f00"
        android:strokeWidth="1.05104995"/>
    <path 
        android:pathData="M191.206,135.874C217.473,92.581 200.247,68.776 223.62,57.621"
        android:strokeColor="#7b3f00"
        android:strokeWidth="2.30999994"/>
    <path
        android:fillColor="#fcd116"
        android:pathData="m175,175h23.1l-23.1,-127.05 -23.1,127.05h23.1L175,47.95"
        android:strokeColor="#7b3f00"
        android:strokeWidth="2.30999994"/>
    <path
        android:fillColor="#7b3f00"
        android:pathData="m175,175h-23.1,23.1L175,47.95l-23.1,127.05"/>
    <path
        android:fillColor="#fcd116"
        android:pathData="M204.802,156.405 L208.843,135.979C266.87,145.281 260.724,110.322 292.379,126.38 263.06,126.023 276.122,145.412 233.438,163.092"
        android:strokeColor="#7b3f00"
        android:strokeWidth="0.60000002"/>
    <path
        android:fillColor="#7b3f00"
        android:pathData="m204.801,156.401 l9.142,1.647 -0.094,-0.378c24.39,-5.977 37.633,-16.088 48.006,-23.773 5.189,-3.841 9.666,-7.108 14.521,-8.878a21.783,21.783 112.5,0 1,10.074 -1.214C261.271,114.862 262.938,144.643 208.84,135.972Z"
        android:strokeColor="#7b3f00"
        android:strokeWidth="0.273"/>
    <path 
        android:pathData="M214.126,158.794C263.313,146.754 267.964,117.741 292.379,126.38"
        android:strokeColor="#7b3f00"
        android:strokeWidth="0.60000002"/>
    <path
        android:fillColor="#fcd116"
        android:pathData="m175,175 l16.334,16.334 73.504,-106.172 -106.172,73.504 16.334,16.334 89.838,-89.838"
        android:strokeColor="#7b3f00"
        android:strokeWidth="2.30999994"/>
    <path
        android:fillColor="#7b3f00"
        android:pathData="M175,175 L158.665,158.666 175,175 264.838,85.162 158.665,158.666"/>
    <path
        android:fillColor="#fcd116"
        android:pathData="m209.222,182.925 l17.301,-11.586c34.454,47.609 54.827,18.543 65.856,52.282 -20.479,-20.984 -24.323,2.497 -67.006,-15.183"
        android:strokeColor="#7b3f00"
        android:strokeWidth="2.30999994"/>
    <path
        android:fillColor="#7b3f00"
        android:pathData="m209.224,182.921 l5.299,7.629 0.201,-0.334c21.473,13.02 37.987,15.235 50.756,17.136 6.385,0.953 11.861,1.808 16.545,3.99a21.783,21.783 0,0 1,7.981 6.265c-11.479,-24.128 -31.358,-1.892 -63.48,-46.276z"
        android:strokeColor="#7b3f00"
        android:strokeWidth="1.05104995"/>
    <path 
        android:pathData="m214.126,191.207c43.293,26.267 67.098,9.04 78.253,32.413"
        android:strokeColor="#7b3f00"
        android:strokeWidth="2.30999994"/>
    <path
        android:fillColor="#fcd116"
        android:pathData="m175,175v23.1l127.05,-23.1 -127.05,-23.1v23.1h127.05"
        android:strokeColor="#7b3f00"
        android:strokeWidth="2.30999994"/>
    <path
        android:fillColor="#7b3f00"
        android:pathData="m175,175v-23.1,23.1h127.05l-127.05,-23.1"/>
    <path
        android:fillColor="#fcd116"
        android:pathData="m193.595,204.803 l20.426,4.041c-9.302,58.027 25.657,51.881 9.598,83.536 0.357,-29.319 -18.946,-15.74 -36.626,-58.423"
        android:strokeColor="#7b3f00"
        android:strokeWidth="2.30999994"/>
    <path
        android:fillColor="#7b3f00"
        android:pathData="m193.599,204.801 l-1.647,9.142 0.378,-0.094c5.977,24.39 16.088,37.633 23.773,48.006 3.841,5.189 7.108,9.666 8.878,14.521a21.783,21.783 0,0 1,1.214 10.074c8.944,-25.178 -20.836,-23.511 -12.165,-77.609z"
        android:strokeColor="#7b3f00"
        android:strokeWidth="1.05104995"/>
    <path 
        android:pathData="m191.206,214.127c12.039,49.187 41.053,53.838 32.413,78.253"
        android:strokeColor="#7b3f00"
        android:strokeWidth="2.30999994"/>
    <path
        android:fillColor="#fcd116"
        android:pathData="m175,175 l-16.334,16.334 106.172,73.504 -73.504,-106.172 -16.334,16.334 89.838,89.838"
        android:strokeColor="#7b3f00"
        android:strokeWidth="2.30999994"/>
    <path
        android:fillColor="#7b3f00"
        android:pathData="m175,175 l16.334,-16.334 -16.334,16.334 89.838,89.838 -73.504,-106.172"/>
    <path
        android:fillColor="#7b3f00"
        android:pathData="m167.079,209.224 l-7.629,5.299 0.334,0.201c-13.02,21.473 -15.235,37.987 -17.136,50.756 -0.953,6.385 -1.808,11.861 -3.99,16.545a21.783,21.783 0,0 1,-6.265 7.981c24.128,-11.479 1.892,-31.358 46.276,-63.48z"
        android:strokeColor="#7b3f00"
        android:strokeWidth="1.05070865"/>
    <path 
        android:pathData="m158.793,214.127c-26.267,43.293 -9.04,67.098 -32.413,78.253"
        android:strokeColor="#7b3f00"
        android:strokeWidth="2.30929136"/>
    <path
        android:fillColor="#fcd116"
        android:pathData="m175,175h-23.1l23.1,127.05 23.1,-127.05h-23.1v127.05"
        android:strokeColor="#7b3f00"
        android:strokeWidth="2.30929136"/>
    <path
        android:fillColor="#7b3f00"
        android:pathData="m175,175h23.1,-23.1v127.05l23.1,-127.05" />
    <path
        android:fillColor="#7b3f00"
        android:pathData="m175,175 l16.334,16.334 -16.334,-16.334 -89.838,89.838 106.172,-73.504" />
    <path
        android:fillColor="#fcd116"
        android:pathData="M174.999,174.999m-42.35,0a42.35,42.35 0,1 1,84.699 0a42.35,42.35 0,1 1,-84.699 0"
        android:strokeColor="#7b3f00"
        android:strokeWidth="2.30929136"/>
    <path
        android:fillColor="#7b3f00"
        android:pathData="m206.185,158.06c-2.695,3.08 -4.235,-2.31 -13.86,-2.31 -9.625,0 -11.165,5.775 -12.705,4.62 -1.54,-1.155 8.085,-8.085 11.165,-8.47 3.08,-0.385 11.935,2.695 15.4,6.16m-11.165,3.465c2.695,2.31 0.385,7.315 -2.31,7.315 -2.695,0 -7.7,-4.62 -5.39,-7.7" />
    <path
        android:fillColor="#7b3f00"
        android:pathData="m182.315,164.99c0.385,-4.62 4.235,-5.39 10.395,-5.39 6.16,0 8.855,4.62 11.165,5.775 -2.695,0 -5.005,-3.85 -11.165,-3.85 -6.16,0 -6.16,0 -10.395,3.85m1.155,0.77c1.54,-2.31 3.465,2.31 7.7,2.31 4.235,0 6.545,-1.155 9.24,-3.08 2.695,-1.925 -3.85,4.62 -8.085,4.62 -4.235,0 -10.01,-2.31 -8.855,-3.85" />
    <path
        android:fillColor="#7b3f00"
        android:pathData="m153.439,161.141c-1.925,0.77 -5.005,4.619 0,7.314 -3.85,-2.695 -0.77,-6.544 0,-7.314z" />
    <path
        android:fillColor="#7b3f00"
        android:pathData="m196.56,161.141c0.77,0.77 3.85,4.619 0,7.314 5.005,-2.695 1.925,-6.544 0,-7.314z" />
    <path
        android:fillColor="#7b3f00"
        android:pathData="m168.839,177.696c-3.465,0.77 -2.311,5.775 -5.391,6.16 -3.08,0.385 -4.619,3.85 -4.234,3.465 1.925,-1.54 6.16,-2.695 9.24,-2.695 3.08,0 3.85,1.926 6.545,1.926 2.695,0 3.465,-1.926 6.545,-1.926 3.08,0 7.315,1.155 9.24,2.695 0.385,0.385 -1.154,-3.08 -4.234,-3.465 -3.08,-0.385 -1.926,-5.39 -5.391,-6.16 0,1.54 1.154,1.155 1.539,3.465 0,1.925 -3.464,1.925 -4.234,0 0.77,3.08 -1.54,3.08 -3.465,3.08 -1.925,0 -4.235,-0 -3.465,-3.08 -0.77,1.925 -4.234,1.925 -4.234,0 0.385,-2.31 1.539,-1.925 1.539,-3.465z" />
    <path
        android:fillColor="#7b3f00"
        android:pathData="m156.904,190.786c-3.08,2.31 -3.849,3.465 -4.234,6.16 0.923,-1.616 1.377,-2.28 2.078,-3.23 -0.186,-0.08 -0.345,-0.153 -0.537,-0.234 0.224,0.026 0.425,0.062 0.641,0.092 0.466,-0.629 0.879,-1.174 2.053,-2.787z" />
    <path
        android:fillColor="#7b3f00"
        android:pathData="m154.851,193.573c-0.011,0.015 -0.038,0.052 -0.049,0.067 0.481,0.112 0.992,0.164 1.527,0.166 -0.47,-0.083 -0.965,-0.161 -1.479,-0.232z" />
    <path
        android:fillColor="#7b3f00"
        android:pathData="m156.33,193.805c2.401,0.424 4.286,0.976 6.014,1.535 2.155,-0.16 5.127,-0.705 12.656,-0.705 7.529,0 10.501,0.546 12.656,0.705 1.728,-0.559 3.613,-1.111 6.014,-1.535 -4.242,0.015 -9.897,-3.02 -12.51,-3.02 -3.08,0 -3.85,0.77 -6.16,0.77 -2.31,0 -3.08,-0.77 -6.16,-0.77 -2.613,0 -8.267,3.035 -12.51,3.02z" />
    <path
        android:fillColor="#7b3f00"
        android:pathData="m193.67,193.805c0.535,-0.002 1.046,-0.054 1.527,-0.166 -0.011,-0.015 -0.038,-0.051 -0.049,-0.067 -0.514,0.072 -1.008,0.149 -1.479,0.232z" />
    <path
        android:fillColor="#7b3f00"
        android:pathData="m195.148,193.573c0.216,-0.03 0.416,-0.064 0.641,-0.092 -0.192,0.081 -0.352,0.155 -0.537,0.234 0.701,0.95 1.155,1.614 2.078,3.23 -0.385,-2.695 -1.154,-3.85 -4.234,-6.16 1.173,1.613 1.587,2.158 2.053,2.787z" />
    <path
        android:fillColor="#7b3f00"
        android:pathData="m195.252,193.715c-0.004,-0.008 -0.015,-0.023 -0.02,-0.026 -4.018,1.548 -5.433,1.811 -7.576,1.652 -3.65,1.181 -6.659,2.375 -12.656,2.375 -5.997,0 -9.006,-1.194 -12.656,-2.375 -2.143,0.159 -3.558,-0.104 -7.576,-1.652 -0.004,0.008 -0.015,0.023 -0.02,0.026 12.095,5.206 10.772,7.08 20.252,7.08 9.48,0 8.157,-1.874 20.252,-7.08z" />
    <path
        android:fillColor="#7b3f00"
        android:pathData="m154.767,193.688c0.008,-0.011 0.027,-0.038 0.035,-0.049 -0.201,-0.047 -0.403,-0.089 -0.592,-0.158 0.22,0.086 0.352,0.128 0.557,0.207z" />
    <path
        android:fillColor="#7b3f00"
        android:pathData="m195.232,193.688c0.205,-0.079 0.337,-0.121 0.557,-0.207 -0.189,0.069 -0.391,0.112 -0.592,0.158 0.008,0.011 0.027,0.038 0.035,0.049z" />
    <path
        android:fillColor="#7b3f00"
        android:pathData="m143.815,158.06c2.695,3.08 4.235,-2.31 13.86,-2.31 9.625,0 11.165,5.775 12.705,4.62 1.54,-1.155 -8.085,-8.085 -11.165,-8.47 -3.08,-0.385 -11.935,2.695 -15.4,6.16m11.165,3.465c-2.695,2.31 -0.385,7.315 2.31,7.315 2.695,0 7.7,-4.62 5.39,-7.7" />
    <path
        android:fillColor="#7b3f00"
        android:pathData="m167.685,164.99c-0.385,-4.62 -4.235,-5.39 -10.395,-5.39 -6.16,0 -8.855,4.62 -11.165,5.775 2.695,0 5.005,-3.85 11.165,-3.85 6.16,0 6.16,0 10.395,3.85m-1.155,0.77c-1.54,-2.31 -3.465,2.31 -7.7,2.31 -4.235,0 -6.545,-1.155 -9.24,-3.08 -2.695,-1.925 3.85,4.62 8.085,4.62 4.235,0 10.01,-2.31 8.855,-3.85" />
    <path
        android:fillColor="#7b3f00"
        android:pathData="m175,204.26c-1.925,0 -6.93,1.155 0,1.155 6.93,0 1.925,-1.155 0,-1.155" />
</vector>
